raviabc/__init__.py
raviabc/add.py
raviabc/minus.py
raviabc-0.0.1.dist-info/LICENSE
raviabc-0.0.1.dist-info/METADATA
raviabc-0.0.1.dist-info/WHEEL
raviabc-0.0.1.dist-info/top_level.txt
raviabc-0.0.1.dist-info/RECORD
