Metadata-Version: 2.1
Name: raviabc
Version: 0.0.1
Summary: raviabc
Home-page: UNKNOWN
Author: Ravi
Author-email: rg9672826@gmail.com
License: UNKNOWN
Keywords: arithmetic,math,mathematics,python tutorial,avi upadhyay
Platform: UNKNOWN
Classifier: Development Status :: 1 - Planning
Classifier: Intended Audience :: Developers
Classifier: Programming Language :: Python :: 3
Classifier: Operating System :: Unix
Classifier: Operating System :: MacOS :: MacOS X
Classifier: Operating System :: Microsoft :: Windows
License-File: LICENSE
